{
  "Canon": [
    {
      "name": "Canon EOS 1000D"
    },
    {
      "name": "Canon EOS 10D"
    },
    {
      "name": "Canon EOS 1D Mark II"
    },
    {
      "name": "Canon EOS 1D Mark II N"
    },
    {
      "name": "Canon EOS 1D Mark III"
    },
    {
      "name": "Canon EOS 1D Mark IV"
    },
    {
      "name": "Canon EOS 1Ds"
    },
    {
      "name": "Canon EOS 1Ds Mark II"
    },
    {
      "name": "Canon EOS 1Ds Mark III"
    },
    {
      "name": "Canon EOS 20D"
    },
    {
      "name": "Canon EOS 300D"
    },
    {
      "name": "Canon EOS 30D"
    },
    {
      "name": "Canon EOS 350D"
    },
    {
      "name": "Canon EOS 400D"
    },
    {
      "name": "Canon EOS 40D"
    },
    {
      "name": "Canon EOS 450D"
    },
    {
      "name": "Canon EOS 500D"
    },
    {
      "name": "Canon EOS 50D"
    },
    {
      "name": "Canon EOS 550D"
    },
    {
      "name": "Canon EOS 550D pre production"
    },
    {
      "name": "Canon EOS 5D"
    },
    {
      "name": "Canon EOS 5D Mark II"
    },
    {
      "name": "Canon EOS 7D"
    },
    {
      "name": "Canon Powershot G10"
    },
    {
      "name": "Canon Powershot G11"
    },
    {
      "name": "Canon Powershot G9"
    },
    {
      "name": "Canon PowerShot S90"
    },
    {
      "name": "Canon EOS 60D"
    },
    {
      "name": "Canon PowerShot G12"
    },
    {
      "name": "Canon PowerShot S95"
    },
    {
      "name": "Canon EOS 1100D"
    },
    {
      "name": "Canon EOS 600D"
    },
    {
      "name": "Canon PowerShot S100"
    },
    {
      "name": "Canon EOS 1Dx"
    },
    {
      "name": "Canon PowerShot G1X"
    },
    {
      "name": "Canon EOS 5D Mark III"
    },
    {
      "name": "Canon EOS 650D"
    },
    {
      "name": "Canon EOS M"
    },
    {
      "name": "Canon EOS 6D"
    },
    {
      "name": "Canon Powershot G15"
    },
    {
      "name": "Canon Powershot S110"
    },
    {
      "name": "Canon PowerShot SX50 HS"
    },
    {
      "name": "Canon EOS 700D"
    },
    {
      "name": "Canon EOS 100D"
    },
    {
      "name": "Canon EOS 70D"
    },
    {
      "name": "Canon PowerShot G16"
    },
    {
      "name": "Canon PowerShot S120"
    },
    {
      "name": "Canon EOS M2"
    },
    {
      "name": "Canon EOS 1200D"
    },
    {
      "name": "Canon PowerShot G1 X Mark II"
    },
    {
      "name": "Canon EOS 7D Mark II"
    },
    {
      "name": "Canon PowerShot G7 X"
    },
    {
      "name": "Canon PowerShot SX60 HS"
    },
    {
      "name": "Canon EOS 5DS"
    },
    {
      "name": "Canon EOS 5DS R"
    },
    {
      "name": "Canon EOS 750D"
    },
    {
      "name": "Canon EOS 760D"
    },
    {
      "name": "Canon EOS M3"
    },
    {
      "name": "Canon PowerShot G3 X"
    },
    {
      "name": "Canon EOS M10"
    },
    {
      "name": "Canon PowerShot G9 X"
    },
    {
      "name": "Canon  EOS-1D X Mark II"
    },
    {
      "name": "Canon EOS 80D"
    },
    {
      "name": "Canon EOS 5D Mark IV"
    },
    {
      "name": "Canon EOS M5"
    },
    {
      "name": "Canon PowerShot G9 X Mark II"
    },
    {
      "name": "Canon EOS M6"
    },
    {
      "name": "Canon EOS 6D Mark II"
    }
  ],
  "Fujifilm": [
    {
      "name": "Fujifilm FinePix S100fs"
    },
    {
      "name": "Fujifilm FinePix S3 Pro"
    },
    {
      "name": "Fujifilm FinePix S5 Pro"
    },
    {
      "name": "Fujifilm FinePix X100"
    },
    {
      "name": "Fujifilm FinePix F550EXR"
    },
    {
      "name": "Fujifilm FinePix F600EXR"
    },
    {
      "name": "Fujifilm FinePix X S1"
    },
    {
      "name": "Fujifilm FinePix X10"
    },
    {
      "name": "Fujifilm FinePix F800EXR"
    },
    {
      "name": "Fujifilm XF1"
    }
  ],
  "Hasselblad": [
    {
      "name": "Hasselblad H3DII 39"
    },
    {
      "name": "Hasselblad H3DII 50"
    }
  ],
  "Konica Minolta": [
    {
      "name": "Konica Minolta DYNAX 5D"
    },
    {
      "name": "Konica Minolta DYNAX 7D"
    }
  ],
  "Leaf": [
    {
      "name": "Leaf Aptus75S"
    }
  ],
  "Leica": [
    {
      "name": "Leica M8"
    },
    {
      "name": "Leica M9"
    },
    {
      "name": "Leica M9 P"
    },
    {
      "name": "Leica M Typ 240"
    },
    {
      "name": "Leica S"
    },
    {
      "name": "Leica M-E Typ 220"
    },
    {
      "name": "Leica C"
    },
    {
      "name": "Leica X Vario"
    },
    {
      "name": "Leica T"
    },
    {
      "name": "Leica Q Typ 116"
    },
    {
      "name": "Leica SL (Typ 601)"
    }
  ],
  "Mamiya": [
    {
      "name": "Mamiya ZD Back"
    }
  ],
  "Nikon": [
    {
      "name": "Nikon D200"
    },
    {
      "name": "Nikon D2H"
    },
    {
      "name": "Nikon D2X"
    },
    {
      "name": "Nikon D2Xs"
    },
    {
      "name": "Nikon D3"
    },
    {
      "name": "Nikon D300"
    },
    {
      "name": "Nikon D3000"
    },
    {
      "name": "Nikon D300s"
    },
    {
      "name": "Nikon D3s"
    },
    {
      "name": "Nikon D3X"
    },
    {
      "name": "Nikon D40"
    },
    {
      "name": "Nikon D40X"
    },
    {
      "name": "Nikon D50"
    },
    {
      "name": "Nikon D5000"
    },
    {
      "name": "Nikon D60"
    },
    {
      "name": "Nikon D70"
    },
    {
      "name": "Nikon D700"
    },
    {
      "name": "Nikon D70s"
    },
    {
      "name": "Nikon D80"
    },
    {
      "name": "Nikon D90"
    },
    {
      "name": "Nikon Coolpix P6000"
    },
    {
      "name": "Nikon D3100"
    },
    {
      "name": "Nikon D7000"
    },
    {
      "name": "Nikon Coolpix P7000"
    },
    {
      "name": "Nikon D5100"
    },
    {
      "name": "Nikon Coolpix P7100"
    },
    {
      "name": "Nikon 1 J1"
    },
    {
      "name": "Nikon 1 V1"
    },
    {
      "name": "Nikon D4"
    },
    {
      "name": "Nikon D800"
    },
    {
      "name": "Nikon D3200"
    },
    {
      "name": "Nikon D800E"
    },
    {
      "name": "Nikon 1 J2"
    },
    {
      "name": "Nikon Coolpix P7700"
    },
    {
      "name": "Nikon D600"
    },
    {
      "name": "Nikon 1 V2"
    },
    {
      "name": "Nikon D5200"
    },
    {
      "name": "Nikon 1 S1"
    },
    {
      "name": "Nikon 1 J3"
    },
    {
      "name": "Nikon D7100"
    },
    {
      "name": "Nikon Coolpix A"
    },
    {
      "name": "Nikon Coolpix P330"
    },
    {
      "name": "Nikon Coolpix P7800"
    },
    {
      "name": "Nikon 1 AW1"
    },
    {
      "name": "Nikon D610"
    },
    {
      "name": "Nikon D5300"
    },
    {
      "name": "Nikon Df"
    },
    {
      "name": "Nikon D3300"
    },
    {
      "name": "Nikon Coolpix P340"
    },
    {
      "name": "Nikon D4s"
    },
    {
      "name": "Nikon 1 V3"
    },
    {
      "name": "Nikon 1 J4"
    },
    {
      "name": "Nikon D810"
    },
    {
      "name": "Nikon D750"
    },
    {
      "name": "Nikon D5500"
    },
    {
      "name": "Nikon D7200"
    },
    {
      "name": "Nikon 1 J5"
    },
    {
      "name": "Nikon D500"
    },
    {
      "name": "Nikon D5"
    },
    {
      "name": "Nikon D3400"
    },
    {
      "name": "Nikon D5600"
    },
    {
      "name": "Nikon D7500"
    }
  ],
  "Olympus": [
    {
      "name": "Olympus E3"
    },
    {
      "name": "Olympus E30"
    },
    {
      "name": "Olympus E410"
    },
    {
      "name": "Olympus E420"
    },
    {
      "name": "Olympus E450"
    },
    {
      "name": "Olympus E510"
    },
    {
      "name": "Olympus E520"
    },
    {
      "name": "Olympus E600"
    },
    {
      "name": "Olympus E620"
    },
    {
      "name": "Olympus PEN EP1"
    },
    {
      "name": "Olympus PEN EP2"
    },
    {
      "name": "Olympus PEN EPL1"
    },
    {
      "name": "Olympus SP 565 UZ"
    },
    {
      "name": "Olympus SP 570 UZ"
    },
    {
      "name": "Olympus E5"
    },
    {
      "name": "Olympus PEN EPL2"
    },
    {
      "name": "Olympus XZ1"
    },
    {
      "name": "Olympus PEN EP3"
    },
    {
      "name": "Olympus PEN EPL3"
    },
    {
      "name": "Olympus PEN EPM1"
    },
    {
      "name": "Olympus OM-D E-M5"
    },
    {
      "name": "Olympus PEN E-PM2"
    },
    {
      "name": "Olympus PEN E-PL5"
    },
    {
      "name": "Olympus XZ-2 iHS"
    },
    {
      "name": "Olympus PEN E-P5"
    },
    {
      "name": "Olympus OM-D E-M1"
    },
    {
      "name": "Olympus Stylus1"
    },
    {
      "name": "Olympus OM-D E-M10"
    },
    {
      "name": "Olympus PEN E-PL7"
    },
    {
      "name": "Olympus OM-D E-M5 Mark II"
    },
    {
      "name": "Olympus OM-D E-M10 Mark II"
    },
    {
      "name": "Olympus PEN-F"
    },
    {
      "name": "Olympus OM-D E-M1 Mark II"
    }
  ],
  "Panasonic": [
    {
      "name": "Panasonic DMC FZ28"
    },
    {
      "name": "Panasonic Lumix DMC FX150"
    },
    {
      "name": "Panasonic Lumix DMC G1"
    },
    {
      "name": "Panasonic Lumix DMC GF1"
    },
    {
      "name": "Panasonic Lumix DMC GH1"
    },
    {
      "name": "Panasonic Lumix DMC L10"
    },
    {
      "name": "Panasonic Lumix DMC LX3"
    },
    {
      "name": "Panasonic Lumix DMC G10"
    },
    {
      "name": "Panasonic Lumix DMC G2"
    },
    {
      "name": "Panasonic Lumix DMC GH2"
    },
    {
      "name": "Panasonic Lumix DMC LX5"
    },
    {
      "name": "Panasonic Lumix DMC GF2"
    },
    {
      "name": "Panasonic Lumix DMC G3"
    },
    {
      "name": "Panasonic LUMIX DMC-FZ150"
    },
    {
      "name": "Panasonic Lumix DMC GX1"
    },
    {
      "name": "Panasonic Lumix DMC GF3"
    },
    {
      "name": "Panasonic Lumix DMC GF5"
    },
    {
      "name": "Panasonic Lumix DMC G5"
    },
    {
      "name": "Panasonic Lumix DMC LX7"
    },
    {
      "name": "Panasonic LUMIX DMC-FZ200"
    },
    {
      "name": "Panasonic Lumix DMC-GH3"
    },
    {
      "name": "Panasonic Lumix DMC GF6"
    },
    {
      "name": "Panasonic LUMIX DMC-G6"
    },
    {
      "name": "Panasonic LUMIX DMC-LF1"
    },
    {
      "name": "Panasonic Lumix DMC-FZ70"
    },
    {
      "name": "Panasonic Lumix DMC-GX7"
    },
    {
      "name": "Panasonic Lumix DMC-GM1"
    },
    {
      "name": "Panasonic Lumix DMC-GH4"
    },
    {
      "name": "Panasonic Lumix DMC-FZ1000"
    },
    {
      "name": "Panasonic Lumix DMC-GM5"
    },
    {
      "name": "Panasonic Lumix DMC-LX100"
    },
    {
      "name": "Panasonic Lumix DMC-ZS50"
    },
    {
      "name": "Panasonic Lumix DMC-FZ330"
    },
    {
      "name": "Panasonic Lumix DMC-GX8"
    },
    {
      "name": "Panasonic Lumix DMC-ZS60"
    },
    {
      "name": "Panasonic Lumix DMC-ZS100"
    },
    {
      "name": "Panasonic Lumix DMC-GX80"
    },
    {
      "name": "Panasonic Lumix DMC-FZ2000"
    },
    {
      "name": "Panasonic Lumix DMC LX10"
    },
    {
      "name": "Panasonic Lumix DMC-G80"
    },
    {
      "name": "Panasonic Lumix DC-GH5"
    }
  ],
  "Pentax": [
    {
      "name": "Pentax K10D"
    },
    {
      "name": "Pentax K200D"
    },
    {
      "name": "Pentax K20D"
    },
    {
      "name": "Pentax K7"
    },
    {
      "name": "Pentax KM"
    },
    {
      "name": "Pentax Kx"
    },
    {
      "name": "Pentax 645D"
    },
    {
      "name": "Pentax Kr"
    },
    {
      "name": "Pentax K5"
    },
    {
      "name": "Pentax Q"
    },
    {
      "name": "Pentax K 01"
    },
    {
      "name": "Pentax K-30"
    },
    {
      "name": "Pentax Q10"
    },
    {
      "name": "Pentax K-5 II"
    },
    {
      "name": "Pentax K-5 IIs"
    },
    {
      "name": "Pentax MX-1"
    },
    {
      "name": "Pentax K-50"
    },
    {
      "name": "Pentax K-500"
    },
    {
      "name": "Pentax K-3"
    },
    {
      "name": "Pentax K-S1"
    },
    {
      "name": "Pentax K-3 II"
    },
    {
      "name": "Pentax K-1"
    }
  ],
  "Phase One": [
    {
      "name": "Phase One P40 Plus"
    },
    {
      "name": "Phase One P45 Plus"
    },
    {
      "name": "Phase One P65 Plus"
    },
    {
      "name": "Phase One IQ180 Digital Back"
    }
  ],
  "Samsung": [
    {
      "name": "Samsung GX 20"
    },
    {
      "name": "Samsung NX 10"
    },
    {
      "name": "Samsung NX 100"
    },
    {
      "name": "Samsung EX1"
    },
    {
      "name": "Samsung NX 11"
    },
    {
      "name": "Samsung NX 200"
    },
    {
      "name": "Samsung NX 1000"
    },
    {
      "name": "Samsung NX 20"
    },
    {
      "name": "Samsung NX 210"
    },
    {
      "name": "Samsung EX2F"
    },
    {
      "name": "Samsung NX 300"
    },
    {
      "name": "Samsung NX1100"
    },
    {
      "name": "Samsung NX2000"
    },
    {
      "name": "Samsung GALAXY NX"
    },
    {
      "name": "Samsung NX 30"
    },
    {
      "name": "Samsung NX1"
    },
    {
      "name": "Samsung NX500"
    },
    {
      "name": "Samsung Galaxy S6 Edge"
    }
  ],
  "Sony": [
    {
      "name": "Sony Alpha 100"
    },
    {
      "name": "Sony Alpha 200"
    },
    {
      "name": "Sony Alpha 230"
    },
    {
      "name": "Sony Alpha 300"
    },
    {
      "name": "Sony Alpha 330"
    },
    {
      "name": "Sony Alpha 350"
    },
    {
      "name": "Sony Alpha 380"
    },
    {
      "name": "Sony Alpha 450"
    },
    {
      "name": "Sony Alpha 500"
    },
    {
      "name": "Sony Alpha 550"
    },
    {
      "name": "Sony Alpha 700"
    },
    {
      "name": "Sony Alpha 850"
    },
    {
      "name": "Sony Alpha 900"
    },
    {
      "name": "Sony NEX3"
    },
    {
      "name": "Sony NEX5"
    },
    {
      "name": "Sony Alpha 290"
    },
    {
      "name": "Sony Alpha 390"
    },
    {
      "name": "Sony SLT Alpha 33"
    },
    {
      "name": "Sony SLT Alpha 55"
    },
    {
      "name": "Sony Alpha 580"
    },
    {
      "name": "Sony Alpha 560"
    },
    {
      "name": "Sony NEX-C3"
    },
    {
      "name": "Sony SLT Alpha 35"
    },
    {
      "name": "Sony SLT Alpha 77"
    },
    {
      "name": "Sony SLT Alpha 65"
    },
    {
      "name": "Sony NEX-7"
    },
    {
      "name": "Sony NEX-5N"
    },
    {
      "name": "Sony SLT Alpha 57"
    },
    {
      "name": "Sony NEX-F3"
    },
    {
      "name": "Sony SLT Alpha 37"
    },
    {
      "name": "Sony Cyber-shot DSC-RX100"
    },
    {
      "name": "Sony NEX-5R"
    },
    {
      "name": "Sony Cyber-shot DSC-RX1"
    },
    {
      "name": "Sony NEX-6"
    },
    {
      "name": "Sony SLT Alpha 99"
    },
    {
      "name": "Sony NEX-3N"
    },
    {
      "name": "Sony SLT Alpha 58"
    },
    {
      "name": "Sony Cyber-shot DSC-RX1R"
    },
    {
      "name": "Sony Cyber-shot DSC-RX100 II"
    },
    {
      "name": "Sony NEX-5T"
    },
    {
      "name": "Sony A3000"
    },
    {
      "name": "Sony A7"
    },
    {
      "name": "Sony Cyber-shot DSC-RX10"
    },
    {
      "name": "Sony A7R"
    },
    {
      "name": "Sony A5000"
    },
    {
      "name": "Sony A6000"
    },
    {
      "name": "Sony A7S"
    },
    {
      "name": "Sony SLT Alpha 77 II"
    },
    {
      "name": "Sony Cyber-shot DSC RX100 III"
    },
    {
      "name": "Sony A5100"
    },
    {
      "name": "Sony A7 II"
    },
    {
      "name": "Sony Cyber-shot DSC-RX100 IV"
    },
    {
      "name": "Sony Cyber-shot DSC-RX10 II"
    },
    {
      "name": "Sony A7R II"
    },
    {
      "name": "Sony A7S II"
    },
    {
      "name": "Sony Cyber-shot DSC-RX1R II"
    },
    {
      "name": "Sony SLT Alpha 68"
    },
    {
      "name": "Sony Cybershot DSC-RX10 III"
    },
    {
      "name": "Sony A6300"
    },
    {
      "name": "Sony SLT Alpha 99 II"
    },
    {
      "name": "Sony A6500"
    },
    {
      "name": "Sony Cyber-shot DSC-RX100 V"
    },
    {
      "name": "Sony a9"
    }
  ],
  "Ricoh": [
    {
      "name": "Ricoh GR"
    },
    {
      "name": "Ricoh GR II"
    }
  ],
  "Nokia": [
    {
      "name": "Nokia Lumia 1020"
    },
    {
      "name": "Nokia Lumia 1520"
    }
  ],
  "DxO": [
    {
      "name": "DxO ONE"
    },
    {
      "name": "DxO ONE SuperRAW Plus"
    }
  ],
  "DJI": [
    {
      "name": "DJI Phantom 4"
    },
    {
      "name": "DJI Phantom4 Pro"
    },
    {
      "name": "DJI Zenmuse X4S"
    },
    {
      "name": "DJI Zenmuse X5S"
    }
  ],
  "GoPro": [
    {
      "name": "GoPro HERO5 Black"
    }
  ],
  "YUNEEC": [
    {
      "name": "YUNEEC Breeze 4K"
    }
  ]
}